AstecManager/Manager.py
AstecManager/__init__.py
AstecManager/omerotools.py
AstecManager/atlas/__init__.py
AstecManager/atlas/pm1.xml
AstecManager/atlas/pm3.xml
AstecManager/atlas/pm4.xml
AstecManager/atlas/pm5.xml
AstecManager/atlas/pm7.xml
AstecManager/atlas/pm8.xml
AstecManager/atlas/pm9.xml
AstecManager/libs/analyze.py
AstecManager/libs/contourlib.py
AstecManager/libs/data.py
AstecManager/libs/ioproperties.py
AstecManager/libs/jsonlib.py
AstecManager/libs/lineage.py
AstecManager/libs/lineage_distance.py
AstecManager/libs/ImageHandling/IO.py
AstecManager/libs/ImageHandling/__init__.py
AstecManager/libs/ImageHandling/inrimage.py
AstecManager/libs/ImageHandling/metaimage.py
AstecManager/libs/ImageHandling/spatial_image.py
astecmanager-1.0.9.dist-info/licenses/LICENSE.txt
astecmanager-1.0.9.dist-info/METADATA
astecmanager-1.0.9.dist-info/WHEEL
astecmanager-1.0.9.dist-info/top_level.txt
astecmanager-1.0.9.dist-info/RECORD
