Metadata-Version: 2.4
Name: AstecManager
Version: 1.0.9
Summary: This package creates a management system to run the ASTEC algorithms for developmental biology live imaging. 
Home-page: https://gite.lirmm.fr/bgallean/astecmanagerelease
Author: Benjamin GALLEAN
Author-email: benjamin.gallean@crbm.cnrs.fr
Project-URL: Bug Tracker, https://gite.lirmm.fr/bgallean/astecmanagerelease/-/issues
Classifier: Programming Language :: Python :: 3.10
Classifier: License :: OSI Approved :: MIT License
Classifier: Operating System :: OS Independent
License-File: LICENSE.txt
Requires-Dist: nibabel==5.2.1
Requires-Dist: numpy==1.26.4
Requires-Dist: scipy==1.12.0
Requires-Dist: scikit-image==0.22.0
Requires-Dist: importlib_resources==6.3.0
Requires-Dist: pandas==2.2.1
Requires-Dist: seaborn==0.13.2
Requires-Dist: tifffile==2024.2.12
Requires-Dist: ezomero==2.1.0
Requires-Dist: matplotlib==3.8.3
Requires-Dist: h5py==3.10.0
Requires-Dist: dataclasses==0.6
Requires-Dist: morphonet==2.2.11
Requires-Dist: Markdown==3.5.2
Requires-Dist: pydrive2==1.19.0
Requires-Dist: pillow==9.2.0
Requires-Dist: python-docx==1.1.0
Requires-Dist: opencv-python==4.9.0.80
Requires-Dist: tqdm==4.67.1
Dynamic: author
Dynamic: author-email
Dynamic: classifier
Dynamic: description
Dynamic: description-content-type
Dynamic: home-page
Dynamic: license-file
Dynamic: project-url
Dynamic: requires-dist
Dynamic: summary
